wiredflow/__init__.py
wiredflow/files/json_in_my_custom_name.json
wiredflow/main/__init__.py
wiredflow/main/actions/__init__.py
wiredflow/main/actions/action_input_http.py
wiredflow/main/actions/action_input_mqtt.py
wiredflow/main/actions/action_interface.py
wiredflow/main/actions/actions_full.py
wiredflow/main/actions/assimilation/__init__.py
wiredflow/main/actions/assimilation/configuration_staging.py
wiredflow/main/actions/assimilation/core_staging.py
wiredflow/main/actions/assimilation/http_staging.py
wiredflow/main/actions/assimilation/interface.py
wiredflow/main/actions/assimilation/mqtt_staging.py
wiredflow/main/actions/assimilation/send_staging.py
wiredflow/main/actions/assimilation/store_staging.py
wiredflow/main/actions/stages/__init__.py
wiredflow/main/actions/stages/configuration_stage.py
wiredflow/main/actions/stages/core_stage.py
wiredflow/main/actions/stages/http_stage.py
wiredflow/main/actions/stages/mqtt_stage.py
wiredflow/main/actions/stages/send_stage.py
wiredflow/main/actions/stages/storage_stage.py
wiredflow/main/build.py
wiredflow/main/data.py
wiredflow/main/flow.py
wiredflow/main/multistep.py
wiredflow/main/pipeline.py
wiredflow/main/store_engines/__init__.py
wiredflow/main/store_engines/csv_engine/__init__.py
wiredflow/main/store_engines/csv_engine/csv_db.py
wiredflow/main/store_engines/json_engine/__init__.py
wiredflow/main/store_engines/json_engine/json_db.py
wiredflow/main/store_engines/mongo_engine/__init__.py
wiredflow/main/store_engines/mongo_engine/mongo_db.py
wiredflow/main/store_engines/preprocessors/__init__.py
wiredflow/main/store_engines/preprocessors/datetime_label.py
wiredflow/main/store_engines/preprocessors/mapping.py
wiredflow/main/store_engines/preprocessors/preprocessing.py
wiredflow/main/store_engines/сustom.py
wiredflow/main/synchronization.py
wiredflow/main/template.py
wiredflow/messages/__init__.py
wiredflow/messages/failures_check.py
wiredflow/metrics/__init__.py
wiredflow/metrics/metric.py
wiredflow/mocks/__init__.py
wiredflow-0.1.0.dist-info/LICENSE
wiredflow-0.1.0.dist-info/METADATA
wiredflow-0.1.0.dist-info/WHEEL
wiredflow-0.1.0.dist-info/RECORD
