Metadata-Version: 2.1
Name: wiredflow
Version: 0.1.0
Summary: Library for constructing ETL (Extract, Transform, Load) services
Author: Dreamlone
Author-email: mik_sar@mail.ru
Requires-Python: >=3.10,<4.0
Classifier: Programming Language :: Python :: 3
Classifier: Programming Language :: Python :: 3.10
Classifier: Programming Language :: Python :: 3.11
Requires-Dist: Jinja2 (==3.0.3)
Requires-Dist: attrs (>=22.2.0,<23.0.0)
Requires-Dist: loguru (>=0.6.0,<0.7.0)
Requires-Dist: mkdocs (>=1.4.2,<2.0.0)
Requires-Dist: paho-mqtt (>=1.6.1,<2.0.0)
Requires-Dist: pymongo (>=4.3.3,<5.0.0)
Requires-Dist: pytest (>=7.2.1,<8.0.0)
Requires-Dist: requests (>=2.28.2,<3.0.0)
Requires-Dist: schedule (>=1.1.0,<2.0.0)
